jsonstreamer/__init__.py
jsonstreamer/jsonstreamer.py
jsonstreamer/tape.py
jsonstreamer/yajl/__init__.py
jsonstreamer/yajl/parse.py
jsonstreamer-1.3.8.dist-info/LICENSE
jsonstreamer-1.3.8.dist-info/METADATA
jsonstreamer-1.3.8.dist-info/WHEEL
jsonstreamer-1.3.8.dist-info/top_level.txt
jsonstreamer-1.3.8.dist-info/RECORD
