Metadata-Version: 2.1
Name: jsonstreamer
Version: 1.3.8
Summary: Provides a SAX-like push parser which works with partial json fragments. Also provides an ObjectStreamer that emits key-value pairs or array elements of the `root` json object/array.Based on the fast c libary yajl
Home-page: https://github.com/kashifrazzaqui/json-streamer
Author: Kashif Razzaqui
Author-email: kashif.razzaqui@gmail.com
License: UNKNOWN
Platform: UNKNOWN
License-File: LICENSE
Requires-Dist: again
